LICENSE.txt
MANIFEST.in
README.md
setup.cfg
setup.py
versioneer.py
helium_client/__init__.py
helium_client/__init__.pyc
helium_client/_helium.c
helium_client/_helium.pxd
helium_client/_helium.pyx
helium_client/_serial.c
helium_client/_serial.h
helium_client/_version.py
helium_client/_version.pyc
helium_client/helium_client.c
helium_client.egg-info/PKG-INFO
helium_client.egg-info/SOURCES.txt
helium_client.egg-info/dependency_links.txt
helium_client.egg-info/requires.txt
helium_client.egg-info/top_level.txt
helium_client/helium-client/.clang-format
helium_client/helium-client/.git
helium_client/helium-client/.gitignore
helium_client/helium-client/.travis.yml
helium_client/helium-client/LICENSE.txt
helium_client/helium-client/Makefile
helium_client/helium-client/README.md
helium_client/helium-client/helium-client-error.h
helium_client/helium-client/helium-client.c
helium_client/helium-client/helium-client.h
helium_client/helium-client/cauterize/atom_api.c
helium_client/helium-client/cauterize/atom_api.h
helium_client/helium-client/cauterize/atom_api.scm
helium_client/helium-client/cauterize/cauterize.c
helium_client/helium-client/cauterize/cauterize.h
helium_client/helium-client/cauterize/config_api.c
helium_client/helium-client/cauterize/config_api.h
helium_client/helium-client/cauterize/config_api.scm
helium_client/helium-client/cauterize/config_api.spec